{
  "BtnParametrosGenerales": {
    "GetFieldBy": "xpath",
    "ValueToFind": "/html[1]/body[1]/oph-root[1]/oph-side-nav-outer-toolbar[1]/dx-drawer[1]/div[1]/div[1]/oph-side-navigation-menu[1]/div[1]/dx-tree-view[1]/div[1]/div[1]/div[1]/div[1]/ul[1]/li[15]/div[1]/div[1]/i[1]"
  },

  "TxtIntentosMaximos": {
    "GetFieldBy": "xpath",
    "ValueToFind": "/html[1]/body[1]/oph-root[1]/oph-side-nav-outer-toolbar[1]/dx-drawer[1]/div[1]/div[2]/div[2]/div[1]/ng-component[1]/div[1]/div[1]/ngb-tabset[1]/div[1]/div[3]/dx-scroll-view[1]/div[1]/div[1]/div[1]/div[2]/oph-parameters-admin[1]/div[1]/div[1]/div[1]/dx-form[1]/div[1]/div[1]/div[1]/div[2]/div[1]/div[1]/div[1]/div[1]/div[2]/div[1]/div[1]/div[1]/div[1]/div[1]/div[1]/div[1]/div[1]/div[1]/div[1]/div[1]/div[1]/div[1]/div[1]/div[1]/div[1]/input[1]"
  },

  "TxtTiempoBloqueoIntentosFallidos": {
    "GetFieldBy": "xpath",
    "ValueToFind": "/html[1]/body[1]/oph-root[1]/oph-side-nav-outer-toolbar[1]/dx-drawer[1]/div[1]/div[2]/div[2]/div[1]/ng-component[1]/div[1]/div[1]/ngb-tabset[1]/div[1]/div[3]/dx-scroll-view[1]/div[1]/div[1]/div[1]/div[2]/oph-parameters-admin[1]/div[1]/div[1]/div[1]/dx-form[1]/div[1]/div[1]/div[1]/div[2]/div[1]/div[1]/div[1]/div[1]/div[2]/div[1]/div[1]/div[1]/div[1]/div[1]/div[1]/div[1]/div[2]/div[1]/div[1]/div[1]/div[1]/div[1]/div[1]/div[1]/div[1]/input[1]"
  },
  "TxtDiasCambioContraseña": {
    "GetFieldBy": "xpath",
    "ValueToFind": "/html[1]/body[1]/oph-root[1]/oph-side-nav-outer-toolbar[1]/dx-drawer[1]/div[1]/div[2]/div[2]/div[1]/ng-component[1]/div[1]/div[1]/ngb-tabset[1]/div[1]/div[3]/dx-scroll-view[1]/div[1]/div[1]/div[1]/div[2]/oph-parameters-admin[1]/div[1]/div[1]/div[1]/dx-form[1]/div[1]/div[1]/div[1]/div[2]/div[1]/div[1]/div[1]/div[1]/div[2]/div[1]/div[1]/div[1]/div[1]/div[1]/div[1]/div[1]/div[1]/div[1]/div[2]/div[1]/div[1]/div[1]/div[1]/div[1]/div[1]/input[1]"
  },

  "TxtTiempoSesion": {
    "GetFieldBy": "xpath",
    "ValueToFind": "/html[1]/body[1]/oph-root[1]/oph-side-nav-outer-toolbar[1]/dx-drawer[1]/div[1]/div[2]/div[2]/div[1]/ng-component[1]/div[1]/div[1]/ngb-tabset[1]/div[1]/div[3]/dx-scroll-view[1]/div[1]/div[1]/div[1]/div[2]/oph-parameters-admin[1]/div[1]/div[1]/div[1]/dx-form[1]/div[1]/div[1]/div[1]/div[2]/div[1]/div[1]/div[1]/div[1]/div[2]/div[1]/div[1]/div[1]/div[1]/div[1]/div[1]/div[1]/div[2]/div[1]/div[2]/div[1]/div[1]/div[1]/div[1]/div[1]/div[1]/input[1]"
  },

  "TxtSesionesConcurrentes": {
    "GetFieldBy": "xpath",
    "ValueToFind": "/html[1]/body[1]/oph-root[1]/oph-side-nav-outer-toolbar[1]/dx-drawer[1]/div[1]/div[2]/div[2]/div[1]/ng-component[1]/div[1]/div[1]/ngb-tabset[1]/div[1]/div[3]/dx-scroll-view[1]/div[1]/div[1]/div[1]/div[2]/oph-parameters-admin[1]/div[1]/div[1]/div[1]/dx-form[1]/div[1]/div[1]/div[1]/div[2]/div[1]/div[1]/div[1]/div[1]/div[2]/div[1]/div[1]/div[1]/div[1]/div[1]/div[1]/div[1]/div[1]/div[1]/div[3]/div[1]/div[1]/div[1]/div[1]/div[1]/div[1]/input[1]"
  },

  "TxtTiempoInactividad": {
    "GetFieldBy": "xpath",
    "ValueToFind": "/html[1]/body[1]/oph-root[1]/oph-side-nav-outer-toolbar[1]/dx-drawer[1]/div[1]/div[2]/div[2]/div[1]/ng-component[1]/div[1]/div[1]/ngb-tabset[1]/div[1]/div[3]/dx-scroll-view[1]/div[1]/div[1]/div[1]/div[2]/oph-parameters-admin[1]/div[1]/div[1]/div[1]/dx-form[1]/div[1]/div[1]/div[1]/div[2]/div[1]/div[1]/div[1]/div[1]/div[2]/div[1]/div[1]/div[1]/div[1]/div[1]/div[1]/div[1]/div[2]/div[1]/div[3]/div[1]/div[1]/div[1]/div[1]/div[1]/div[1]/input[1]"
  },
  "BtnRecursos": {
    "GetFieldBy": "xpath",
    "ValueToFind": "(//i[@class='cls6 dx-icon fa-cubes fas'])[1]"
  },
  "TxtRecuperarContrasena": {
    "GetFieldBy": "xpath",
    "ValueToFind": "/html[1]/body[1]/oph-root[1]/oph-side-nav-outer-toolbar[1]/dx-drawer[1]/div[1]/div[2]/div[2]/div[1]/ng-component[1]/div[1]/div[1]/ngb-tabset[1]/div[1]/div[3]/dx-scroll-view[1]/div[1]/div[1]/div[1]/div[2]/oph-parameters-admin[1]/div[1]/div[1]/div[1]/dx-form[1]/div[1]/div[1]/div[1]/div[1]/div[1]/div[1]/div[1]/div[1]/div[1]/div[1]/div[1]/div[1]/div[1]/div[1]/div[2]/div[1]/div[1]/div[1]/div[1]/div[1]/div[1]/div[1]/div[1]/div[3]/div[1]/div[1]/div[1]/div[1]/div[1]/div[1]/div[1]/div[1]/div[1]/input[1]"
  },
  "BtnGuardar": {
    "GetFieldBy": "xpath",
    "ValueToFind": "/html[1]/body[1]/oph-root[1]/oph-side-nav-outer-toolbar[1]/dx-drawer[1]/div[1]/div[2]/div[2]/div[1]/ng-component[1]/div[1]/div[1]/ngb-tabset[1]/div[1]/div[3]/dx-scroll-view[1]/div[1]/div[1]/div[1]/div[2]/oph-parameters-admin[1]/oph-tool-bar[1]/ngb-tabset[1]/div[1]/div[1]/div[1]/div[1]/div[1]/div[1]/div[1]"
  },
  "TxtCamposObligatorios": {
    "GetFieldBy": "xpath",
    "ValueToFind": "(//div[@class='dx-form-validation-summary dx-validationsummary dx-widget dx-collection'])[1]"
  },
  "Mensaje_confirmacion": {
    "GetFieldBy": "xpath",
    "ValueToFind": "//div[contains(text(),'Si se guardan los cambios se debe cerrar la sesion')]"
  },
  "BtnSi": {
    "GetFieldBy": "xpath",
    "ValueToFind": "//div[@aria-label='Sí']//div[@class='dx-button-content']"
  },

  "DigitalWare": {
    "GetFieldBy": "xpath",
    "ValueToFind": "//div[@class='Authentication__form-logo-container']"
  },
  "BtnPerfil": {
    "GetFieldBy": "xpath",
    "ValueToFind": "//img[@src='assets/images/placeholder-user.jpg']"
  },

  "BtnBloquearSesion": {
    "GetFieldBy": "xpath",
    "ValueToFind": "//span[normalize-space()='Bloquear Sesión']"
  },

  "BtnCierreSesion": {
    "GetFieldBy": "xpath",
    "ValueToFind": "//span[normalize-space()='Cerrar Sesión']"
  },

  "TxtSesionBloqueada": {
    "GetFieldBy": "xpath",
    "ValueToFind": "//h1[normalize-space()='Sesión bloqueada']"
  },
  "textPassword": {
    "GetFieldBy": "xpath",
    "ValueToFind": "/html[1]/body[1]/div[2]/div[1]/div[1]/div[1]/div[1]/div[1]/div[1]/div[2]/div[1]/dx-form[1]/div[1]/div[1]/div[1]/div[1]/div[1]/div[1]/div[1]/div[1]/div[1]/div[1]/div[1]/div[1]/div[1]/div[1]/div[1]/div[1]/div[1]/div[1]/div[1]/input[1]"
  },

  "BtnDesbloquearSesion": {
    "GetFieldBy": "xpath",
    "ValueToFind": "/html[1]/body[1]/div[2]/div[1]/div[1]/div[1]/div[1]/div[1]/div[1]/div[2]/div[1]/dx-form[1]/div[1]/div[1]/div[1]/div[1]/div[1]/div[1]/div[1]/div[1]/div[1]/div[1]/div[1]/div[1]/div[2]/div[1]/div[1]/div[1]/div[1]"
  },
  "Home": {
    "GetFieldBy": "xpath",
    "ValueToFind": "/html[1]/body[1]/oph-root[1]/oph-side-nav-outer-toolbar[1]/dx-drawer[1]/div[1]/div[2]/div[2]/div[1]/ng-component[1]/div[1]/div[1]/ngb-tabset[1]/div[1]/div[1]/oph-home-category-container[1]/div[1]/div[1]/dx-scroll-view[1]/div[1]/div[1]/div[1]"
  },
  "BtnAlmacenamientoStorage": {
    "GetFieldBy": "xpath",
    "ValueToFind": "/html[1]/body[1]/oph-root[1]/oph-side-nav-outer-toolbar[1]/dx-drawer[1]/div[1]/div[2]/div[2]/div[1]/ng-component[1]/div[1]/div[1]/ngb-tabset[1]/div[1]/div[3]/dx-scroll-view[1]/div[1]/div[1]/div[1]/div[2]/oph-parameters-admin[1]/div[1]/div[1]/div[1]/dx-form[1]/div[1]/div[1]/div[1]/div[1]/div[1]/div[1]/div[1]/div[1]/div[1]/div[1]/div[1]/div[1]/div[1]/div[1]/div[2]/div[1]/div[1]/div[1]/div[1]/div[1]/div[1]/div[1]/div[1]/div[4]/div[1]/div[3]/div[1]/div[1]/div[1]/div[1]/div[1]/div[1]/div[1]/input[1]"
  },
  "SelectLocalStorage": {
    "GetFieldBy": "xpath",
    "ValueToFind": "//div[contains(text(),'LocalStorage')]"
  },

  "SesionBloqueada": {
    "GetFieldBy": "xpath",
    "ValueToFind": "//h1[normalize-space()='Sesión bloqueada']"
  },
  "BtnCerrarSesion": {
    "GetFieldBy": "xpath",
    "ValueToFind": "//span[normalize-space()='Cerrar Sesión']"
  }


}